[
  {
    "id": "d487db5f-34da-41db-8c2c-ab271398ffa6",
    "data": [
      {
        "text": "How do you go back a stage in the EPA",
        "userDefined": false
      }
    ],
    "isTemplate": false,
    "count": 0,
    "updated": 1536581410
  },
  {
    "id": "98b8c5df-a04b-4587-82a1-e0fe3bd90523",
    "data": [
      {
        "text": "Can you go back to a closed part of the appraisal process",
        "userDefined": false
      }
    ],
    "isTemplate": false,
    "count": 0,
    "updated": 1536581410
  },
  {
    "id": "7d4bd6fa-8fce-4133-8c37-03fe53206809",
    "data": [
      {
        "text": "How do I re-open a step?",
        "userDefined": false
      }
    ],
    "isTemplate": false,
    "count": 0,
    "updated": 1536581410
  }
]