[
  {
    "id": "849fc1bf-527d-4e73-9129-ff2743d446e1",
    "data": [
      {
        "text": "How do I create my development plan?",
        "userDefined": false
      }
    ],
    "isTemplate": false,
    "count": 0,
    "updated": 1536581498
  },
  {
    "id": "ff59ffec-5498-4b80-a3fe-4d8d457d1fde",
    "data": [
      {
        "text": "Building a development plan in Ingenium",
        "userDefined": false
      }
    ],
    "isTemplate": false,
    "count": 0,
    "updated": 1536581498
  }
]